{"summary":{"九寮子埔":["22342,全"],"九芎坑":["22341,全"],"二格路":["22391,全"],"八分寮":["22341,全"],"十八重溪":["22341,全"],"下紙寮坑":["22341,全"],"下橫坪":["22342,全"],"上橫坪":["22342,全"],"大格門":["22342,全"],"大崙":["22342,全"],"大湖格":["22341,全"],"大溪墘":["22341,全"],"小粗坑巷":["22342,全"],"中楒仔腳":["22342,全"],"內楒仔腳":["22342,全"],"天車":["22391,全"],"月扇湖":["22342,全"],"火燒樟":["22391,全"],"北宜路４段":["22391,全"],"北宜路４段栳寮巷":["22391,全"],"北宜路５段":["22391,全"],"北宜路５段十股寮巷":["22391,全"],"北宜路５段土巷":["22391,全"],"北宜路５段大湖巷":["22391,全"],"北宜路５段五郎寮巷":["22391,全"],"北宜路５段火燒樟巷":["22391,連  28號以下"],"北宜路５段竹坑巷":["22391,全"],"北宜路５段坑內巷":["22391,全"],"北宜路５段崙尾寮巷":["22391,全"],"北宜路５段雷公坡巷":["22391,全"],"北宜路５段潭腰巷":["22391,全"],"北宜路５段濕水子巷":["22391,全"],"北宜路６段十三股巷":["22391,全"],"北宜路６段小金瓜寮巷":["22391,全"],"北宜路６段水底寮巷":["22391,全"],"北宜路６段直潭巷":["22391,全"],"北宜路６段柑腳巷":["22391,全"],"北宜路６段塗潭巷":["22391,全"],"北宜路６段獅仔頭坑巷":["22391,全"],"半路店":["22342,全"],"四分子路":["22342,全"],"四分子路小粗坑巷":["22391,全"],"外按":["22342,全"],"外楒仔腳":["22342,全"],"玉桂嶺":["22341,全"],"石汐路":["22341,全"],"石崁":["22342,全"],"石碇子埔":["22341,全"],"石碇西街":["22342,全"],"石碇東街":["22342,全"],"光明路":["22341,全"],"光明路九層坪巷":["22341,全"],"光明路耳空龜巷":["22341,全"],"光明路頂紙寮坑巷":["22341,全"],"吊橋":["22341,全"],"西勢坑":["22341,全"],"串空湖":["22341,全"],"冷飯坑":["22341,全"],"南勢坑":["22341,全"],"後坑子":["22391,全"],"員山子":["22342,全"],"員潭子坑":["22342,全"],"峯頭":["22341,全"],"烏塗窟":["22342,全"],"崩山":["22342,全"],"排寮":["22341,全"],"深按":["22341,全"],"蛇舌子":["22342,全"],"蚯蚓坑":["22341,全"],"番子坑":["22341,全"],"華梵路":["22301,連   2號以下"],"新興坑":["22341,全"],"楓子林":["22341,全"],"溪邊寮":["22342,全"],"樟空子":["22342,全"],"模乳巷":["22342,全"],"蓬菜寮":["22342,全"],"橫坪":["22342,全"],"磨石坑":["22342,全"],"雙溪":["22341,全"],"藤寮坑":["22341,全"],"湳子":["22342,全"],"湳窟":["22342,全"],"碇南路２段":["22341,全"],"碇南路２段松柏崎巷":["22341,全"],"碇南路２段鹿窟巷":["22341,全"],"碇格路２段":["22391,全"]}}