{"summary":{"三民路":["96142,單 199號以下","96142,雙 166號以下","96143,雙 168號至 216號","96143,單 201號至 259號"],"上海街":["96142,全"],"上麒麟路":["96142,全"],"大仁街":["96145,單  69號以下","96145,雙  26號以下","96143,雙  32號以上","96143,單  71號以上"],"大同路":["96142,全"],"大勇街":["96145,單  61號以下","96145,雙  36號以下","96143,連  70號以上"],"大智街":["96145,單  55號以下","96145,雙  50號以下","96143,雙  52號至  70號","96143,單  57號至  77號"],"小馬路":["96144,全"],"中山東路":["96145,單  87號以下","96145,雙  84號以下","96143,雙  86號至 200號","96143,單  93號至 157號"],"中山路":["96142,單 123號以下","96145,雙 118號以下","96143,單 125號至 167號","96143,雙 132號至 178號"],"中正路":["96145,單 123號以下","96145,雙  66號以下","96143,雙  74號至 114號","96143,單 125號至 189號"],"中華路":["96145,單 151號以下","96145,雙 142號以下","96143,雙 150號至 178號","96143,單 153號至 221號"],"五權路":["96143,全"],"公民路":["96142,全"],"天津街":["96143,全"],"太平路":["96143,全"],"北平街":["96143,全"],"民生路":["96145,單 123號以下","96145,雙 142號以下","96143,單 125號至 255號","96143,雙 144號至 220號"],"民安路":["96143,全"],"民恆路":["96145,單   3號以下","96145,雙   6號以下","96143,單   5號以上","96143,雙   8號以上"],"民族路":["96145,全"],"民富路":["96143,全"],"民豐街":["96143,全"],"民權路":["96145,全"],"玉水橋":["96141,全"],"白蓮路":["96141,全"],"石傘路":["96141,全"],"光復路":["96143,單   5號以下","96145,雙 108號以下","96145,單   7號至 117號"],"吉林街":["96142,全"],"成功路":["96145,全"],"成廣路":["96141,全"],"有恆路":["96143,全"],"和平路":["96144,全"],"宜灣路":["96141,全"],"東海路":["96145,全"],"東發路":["96145,全"],"芝田路":["96143,全"],"長沙街":["96143,全"],"長春街":["96142,全"],"美山路":["96141,全"],"重安路":["96141,全"],"海岸路":["96145,全"],"高台路":["96141,全"],"基翬路":["96141,全"],"都歷路":["96144,全"],"富榮路":["96142,全"],"港邊路":["96143,全"],"跋邊路":["96142,雙全","96144,單全"],"開封街":["96142,全"],"新生路":["96145,單  65號以下","96145,雙  34號以下","96143,雙  42號以上","96143,單  81號至 109號"],"新村路":["96144,全"],"漢口街":["96142,全"],"廣州街":["96143,全"],"興農路":["96141,全"],"隧道路":["96144,全"],"瀋陽街":["96142,全"],"豐田路":["96144,全"],"麒麟路":["96142,全"],"鹽濱路":["96144,全"]}}