{"summary":{"九層嶺":["71249,全"],"三十六崙":["71249,全"],"口埤":["71249,全"],"大同街":["71241,全"],"大坑尾":["71249,全"],"大智路":["71248,全"],"大新路":["71247,全"],"大德路":["71247,全"],"中山路":["71243,全"],"中正路":["71241,全"],"中興路":["71242,全"],"五甲勢":["71249,全"],"仁愛街":["71247,全"],"公園路":["71241,全"],"太平街":["71250,全"],"北勢":["71247,全"],"正新北路":["71248,全"],"正新南路":["71248,全"],"正新路":["71248,全"],"民生路":["71246,全"],"民治路":["71248,全"],"民族街":["71243,全"],"民權街":["71243,全"],"永新路":["71241,全"],"光明路":["71250,全"],"竹子腳":["71244,連 246號以下","71245,　 247號含附號","71244,連 248號以上"],"竹林路":["71243,全"],"那拔林":["71246,全"],"和平街":["71251,全"],"忠孝路":["71251,全"],"牧場":["71246,全"],"知母義":["71248,全"],"金華街１段":["71241,全"],"長青街":["71243,全"],"信義路":["71242,全"],"建國街":["71251,全"],"洋子":["71244,全"],"洋子寮":["71246,全"],"茄冬坑":["71249,全"],"健康路":["71247,全"],"崙子頂":["71244,全"],"頂山腳":["71248,全"],"復興路":["71250,全"],"新和庄":["71249,全"],"蔡厝仔":["71249,全"],"礁坑子":["71249,全"],"護安街":["71241,全"],"唪口":["71247,全"]}}